tests/__init__.py
tests/test_version.py
wap/__init__.py
wap/helper.py
wap/load.py
wap/match.py
wap/structs.py
wap-0.0.2.dist-info/LICENSE
wap-0.0.2.dist-info/METADATA
wap-0.0.2.dist-info/WHEEL
wap-0.0.2.dist-info/top_level.txt
wap-0.0.2.dist-info/RECORD
