Metadata-Version: 2.1
Name: wap
Version: 0.0.2
Summary: Library to parse wappalyzer technologies.json and extracts matches from HTTP responses
Home-page: https://github.com/blackarrowsec/wap
Author: Eloy Perez
Author-email: eloy.perez@tarlogic.com
License: UNKNOWN
Project-URL: Repository, https://github.com/blackarrowsec/wap
Project-URL: Documentation, https://wap.readthedocs.io
Platform: UNKNOWN
Classifier: Programming Language :: Python :: 3
Classifier: License :: OSI Approved :: GNU General Public License v3 (GPLv3)
Requires-Dist: bs4
